nonebot_plugin_elf_rss_next/__init__.py
nonebot_plugin_elf_rss_next/config.py
nonebot_plugin_elf_rss_next/globals.py
nonebot_plugin_elf_rss_next/rss.py
nonebot_plugin_elf_rss_next/scheduler.py
nonebot_plugin_elf_rss_next/utils.py
nonebot_plugin_elf_rss_next/commands/__init__.py
nonebot_plugin_elf_rss_next/commands/add_rss.py
nonebot_plugin_elf_rss_next/commands/cmd_parser.py
nonebot_plugin_elf_rss_next/commands/delete_rss.py
nonebot_plugin_elf_rss_next/commands/edit_rss.py
nonebot_plugin_elf_rss_next/commands/get_manual.py
nonebot_plugin_elf_rss_next/commands/get_rss_info.py
nonebot_plugin_elf_rss_next/commands/list_rss.py
nonebot_plugin_elf_rss_next/rss_parser/__init__.py
nonebot_plugin_elf_rss_next/rss_parser/cache_db_manager.py
nonebot_plugin_elf_rss_next/rss_parser/context.py
nonebot_plugin_elf_rss_next/rss_parser/html_document_processor.py
nonebot_plugin_elf_rss_next/rss_parser/image_processor.py
nonebot_plugin_elf_rss_next/rss_parser/message_sender.py
nonebot_plugin_elf_rss_next/rss_parser/rss_entries_file_operations.py
nonebot_plugin_elf_rss_next/rss_parser/rss_parser.py
nonebot_plugin_elf_rss_next/rss_parser/translation.py
nonebot_plugin_elf_rss_next/rss_parser/utils.py
nonebot_plugin_elf_rss_next-0.1.0.dist-info/METADATA
nonebot_plugin_elf_rss_next-0.1.0.dist-info/WHEEL
nonebot_plugin_elf_rss_next-0.1.0.dist-info/licenses/LICENSE
nonebot_plugin_elf_rss_next-0.1.0.dist-info/RECORD
