Metadata-Version: 2.4
Name: nonebot-plugin-elf-rss-next
Version: 0.1.0
Summary: RSS订阅机器人 ELF_RSS 的独立插件版本
Author-email: liuzhaoze <1045954863@qq.com>
License:                     GNU GENERAL PUBLIC LICENSE
License-File: LICENSE
Requires-Python: >=3.12
Requires-Dist: aiohttp>=3.12.15
Requires-Dist: arrow>=1.3.0
Requires-Dist: async-timeout>=5.0.1
Requires-Dist: asyncache>=0.3.1
Requires-Dist: deep-translator>=1.11.4
Requires-Dist: emoji>=2.14.1
Requires-Dist: feedparser>=6.0.11
Requires-Dist: imagehash>=4.3.2
Requires-Dist: nonebot-adapter-onebot>=2.4.6
Requires-Dist: nonebot-plugin-alconna>=0.59.4
Requires-Dist: nonebot-plugin-apscheduler>=0.5.0
Requires-Dist: nonebot-plugin-localstore>=0.7.4
Requires-Dist: nonebot2>=2.4.3
Requires-Dist: pillow>=11.3.0
Requires-Dist: pyquery>=2.0.1
Requires-Dist: tenacity>=9.1.2
Requires-Dist: tinydb>=4.8.2
Requires-Dist: yarl>=1.20.1
